lightnode/__init__.py
lightnode/announce.py
lightnode/content.py
lightnode/lightnode.py
lightnode/seed.py
lightnode/trx.py
lightnode/pb/__init__.py
lightnode/pb/quorum_pb2.py
lightnode/storage/__init__.py
lightnode/storage/seed.py
lightnode/type/__init__.py
lightnode/type/content.py
lightnode/type/object.py
lightnode/type/seed.py
lightnode/type/trx.py
lightnode/utils/__init__.py
lightnode/utils/aes.py
lightnode/utils/age.py
lightnode/utils/json.py
lightnode/utils/log.py
lightnode/utils/pretty_print.py
quorum_lightnode-0.0.7.dist-info/LICENSE
quorum_lightnode-0.0.7.dist-info/METADATA
quorum_lightnode-0.0.7.dist-info/WHEEL
quorum_lightnode-0.0.7.dist-info/top_level.txt
quorum_lightnode-0.0.7.dist-info/RECORD
