Metadata-Version: 2.1
Name: quorum-lightnode
Version: 0.0.7
Summary: quorum lightnode for python
Home-page: https://github.com/zhangwm404/quorum-lightnode-py
Author: zhangwm404
Author-email: zhangwm404@gmail.com
License: MIT
Platform: any
Classifier: Development Status :: 5 - Production/Stable
Classifier: Intended Audience :: Developers
Classifier: License :: OSI Approved :: MIT License
Classifier: Operating System :: OS Independent
Classifier: Programming Language :: Python
Classifier: Programming Language :: Python :: 3.7
Classifier: Programming Language :: Python :: 3.8
Classifier: Programming Language :: Python :: 3.9
Classifier: Programming Language :: Python :: 3.10
Classifier: Programming Language :: Python :: 3.11
Classifier: Topic :: Software Development :: Libraries :: Python Modules
Requires-Python: >=3.6
License-File: LICENSE
Requires-Dist: requests
Requires-Dist: eth-keys
Requires-Dist: pycryptodome
Requires-Dist: protobuf
Requires-Dist: dataclasses-json
Requires-Dist: pyrage
Provides-Extra: dev
Requires-Dist: pytest (>=3) ; extra == 'dev'
Requires-Dist: coverage ; extra == 'dev'
Requires-Dist: tox ; extra == 'dev'
Requires-Dist: twine ; extra == 'dev'
Requires-Dist: pylint ; extra == 'dev'
Requires-Dist: pylint-protobuf ; extra == 'dev'
